python_on_rails/__init__.py
python_on_rails/common.py
python_on_rails/either.py
python_on_rails/railway.py
python_on_rails/result.py
python_on_rails-1.0.1.dist-info/LICENSE.md
python_on_rails-1.0.1.dist-info/METADATA
python_on_rails-1.0.1.dist-info/WHEEL
python_on_rails-1.0.1.dist-info/top_level.txt
python_on_rails-1.0.1.dist-info/RECORD
