Metadata-Version: 2.1
Name: python-on-rails
Version: 1.0.1
Summary: Railway-Oriented Programming in Python.
Home-page: https://github.com/funnel-io/python-on-rails
Author: The Funnel Dev Team
Author-email: open-source@funnel.io
License: MIT
Project-URL: Bug Reports, https://github.com/funnel-io/python-on-rails/issues
Project-URL: Source, https://github.com/funnel-io/python-on-rails
Keywords: ["Railway-Oriented Programming"]
Classifier: Development Status :: 5 - Production/Stable
Classifier: License :: OSI Approved :: MIT License
Classifier: Programming Language :: Python :: 3
Classifier: Programming Language :: Python :: 3.8
Classifier: Programming Language :: Python :: 3.9
Classifier: Programming Language :: Python :: 3.10
Classifier: Programming Language :: Python :: 3.11
Classifier: Topic :: Software Development :: Libraries
License-File: LICENSE.md
